scripts/__init__.py
scripts/aggregate_dataset_histos.py
scripts/display_histos.py
scripts/py.typed
icecube_simprod_histograms-0.0.2.dist-info/LICENSE
icecube_simprod_histograms-0.0.2.dist-info/METADATA
icecube_simprod_histograms-0.0.2.dist-info/WHEEL
icecube_simprod_histograms-0.0.2.dist-info/top_level.txt
icecube_simprod_histograms-0.0.2.dist-info/RECORD
