Metadata-Version: 2.1
Name: icecube-simprod-histograms
Version: 0.0.2
Summary: Utilities for working with histograms created for simprod
Author-email: IceCube <developers@icecube.wisc.edu>
License: MIT License
Project-URL: Homepage, https://pypi.org/project/icecube-simprod-histograms/
Project-URL: Tracker, https://github.com/icecube/simprod-histogram/issues
Project-URL: Source, https://github.com/icecube/simprod-histogram
Keywords: histogram sampling,simulation,statistics
Classifier: Development Status :: 3 - Alpha
Classifier: Programming Language :: Python :: 3.9
Classifier: Programming Language :: Python :: 3.10
Classifier: Programming Language :: Python :: 3.11
Classifier: Programming Language :: Python :: 3.12
Classifier: Programming Language :: Python :: 3.13
Requires-Python: <3.14,>=3.9
License-File: LICENSE
Requires-Dist: h5py
Provides-Extra: display
Requires-Dist: h5py ; extra == 'display'
Requires-Dist: matplotlib ; extra == 'display'
Provides-Extra: mypy
Requires-Dist: h5py ; extra == 'mypy'
Requires-Dist: pytest ; extra == 'mypy'
Requires-Dist: matplotlib ; extra == 'mypy'
Provides-Extra: tests
Requires-Dist: h5py ; extra == 'tests'
Requires-Dist: pytest ; extra == 'tests'
Requires-Dist: matplotlib ; extra == 'tests'
